geonode_qgis_server/__init__.py
geonode_qgis_server/admin.py
geonode_qgis_server/gis_tools.py
geonode_qgis_server/models.py
geonode_qgis_server/signals.py
geonode_qgis_server/urls.py
geonode_qgis_server/views.py
geonode_qgis_server/migrations/0001_initial.py
geonode_qgis_server/migrations/__init__.py
geonode_qgis_server/static/css/geonode_qgis_server.css
geonode_qgis_server/static/js/geonode_qgis_server.js
geonode_qgis_server/tasks/__init__.py
geonode_qgis_server/tasks/update.py
geonode_qgis_server/templates/geonode_qgis_server/base.html
geonode_qgis_server-0.1.1.dist-info/DESCRIPTION.rst
geonode_qgis_server-0.1.1.dist-info/METADATA
geonode_qgis_server-0.1.1.dist-info/RECORD
geonode_qgis_server-0.1.1.dist-info/WHEEL
geonode_qgis_server-0.1.1.dist-info/metadata.json
geonode_qgis_server-0.1.1.dist-info/top_level.txt
