Metadata-Version: 2.0
Name: geonode-qgis-server
Version: 0.1.1
Summary: Django app to enable QGIS Server in GeoNode.
Home-page: https://github.com/kartoza/geonode_qgis_server
Author: Ismail Sunni
Author-email: imajimatika@gmail.com
License: MIT
Keywords: geonode_qgis_server
Platform: UNKNOWN
Classifier: Development Status :: 3 - Alpha
Classifier: Framework :: Django
Classifier: Framework :: Django :: 1.8
Classifier: Intended Audience :: Developers
Classifier: License :: OSI Approved :: BSD License
Classifier: Natural Language :: English
Classifier: Programming Language :: Python :: 2
Classifier: Programming Language :: Python :: 2.7
Classifier: Programming Language :: Python :: 3
Classifier: Programming Language :: Python :: 3.2
Classifier: Programming Language :: Python :: 3.3
Classifier: Programming Language :: Python :: 3.4
Classifier: Programming Language :: Python :: 3.5
